AND_inciso3.v

module AND_inciso3(
    //output out_7,
    //output out_8,
    output S_OR3,
   
    input X,
    input Y,
    input Z,
    input K,
    input M
    
);

assign noX = !X;
assign noY = !Y;
assign noZ = !Z;
assign noK = !K;
assign noM = !M;

assign out_1 = noX & noY & noM;//implicante 3
assign out_2 = noX & Y & K & M;//implicante 8
assign out_3=  noY & noZ & K;//implicante 4
assign out_4 = X & noY & M; //implicante 10
assign out_5 = X & noZ & M; //implicante 9
assign out_6 = noX & noZ & noM;//implicante 1

assign S_OR3 = (out_1)|(out_2)|(out_3)|(out_4)|(out_5)|(out_6);

endmodule

AND_inciso2.v

module AND_inciso2(
    output S_OR2,
    //output S_OR5,
    input X,
    input Y,
    input Z,
    input K,
    input M   
);

assign noX = !X;
assign noY = !Y;
assign noZ = !Z;
assign noK = !K;
assign noM = !M;

assign S_1 = (noX)&(noY)&(noZ)&(K)&(noM);//m2
assign S_2 = (noX)&(noY)&(noZ)&(K)&(M);//m3
assign S_3 = (noX)&(noY)&(Z)&(noK)&(noM);//m4
assign S_4 = (noX)&(noY)&(Z)&(K)&(noM);//m6
assign S_5 = (noX)&(Y)&(noZ)&(K)&(noM);//m10
assign S_6=  (noX)&(Y)&(noZ)&(K)&(M);//m11
assign S_7 = (noX)&(Y)&(Z)&(K)&(M);//m15
assign S_8 = (X)&(noY)&(noZ)&(noK)&(M);//m17
assign S_9 = (X)&(noY)&(noZ)&(K)&(noM);//m18
assign S_10 = (X)&(noY)&(Z)&(noK)&(M);//m21
assign S_11 = (X)&(Y)&(noZ)&(noK)&(M);//m25
assign S_12 = (X)&(Y)&(noZ)&(K)&(M);//m27

assign S_13 = (noX)&(noY)&(noZ)&(noK)&(noM);//x0
assign S_15 = (noX)&(Y)&(noZ)&(noK)&(noM);//x8
assign S_17 = (X)&(noY)&(noZ)&(K)&(M);//x19
assign S_19 = (X)&(noY)&(Z)&(K)&(M);//x23

assign S_OR2 = (S_1)|(S_2)|(S_3)|(S_4)|(S_5)|(S_6)|(S_7)|(S_8)|(S_9)|(S_10)|(S_11)|(S_12)|(S_13)|(S_15)|(S_17)|(S_19);
//assign S_OR5 = (noX&noY&noZ&K&noM)| (noX&noY&noZ&K&M)| (noX&noY&Z&noK&noM)| (noX&noY&Z&K&noM)| (noX&Y&noZ&K&noM)| (noX&Y&noZ&K&M)| (noX&Y&Z&K&M)| (X&noY&noZ&noK&M)| (X&noY&noZ&K&noM)| (X&noY&Z&noK&M)| (X&Y&noZ&noK&M)| (X&Y&noZ&K&M)|(noX&noY&noZ&noK&noM)|(noX&Y&noZ&noK&noM)|(X&noY&noZ&K&M)|(X&noY&Z&K&M);  

endmodule

test_bench_P1.v
`include "AND_inciso3.v"
`include "AND_inciso2.v"


module Test_bench_P1;
    reg X, Y,Z ,K, M; // Entradas
    wire WS_OR2, WS_OR3,WS_OR4,WS_OR5, Wout_7,Wout_8;  // Salidas
    integer i;

    AND_inciso2 Indtance0 ( WS_OR2,X, Y, Z,K,M);
    AND_inciso3 Indtance1 (WS_OR3, X, Y, Z,K,M);
    
   
    
initial begin

    // Estímulo
    // Para iniciar en 00000
    X <= 0;Y <= 0;Z <= 0;K <= 0;M <= 0;

    for(i = 0; i < 32; i = i + 1) 
        begin
            {X,Y,Z,K,M} = i; 
            #10; 
        end   
end
   
initial begin
    $monitor("A continuacion la tabla de verdad usada:");
    $monitor("X=%0b Y=%0b Z=%0b K=%0b M=%0b ", X,Y,Z,K,M);
    // Crear archivo .vcd para gtkwave
    $dumpfile("Prueba_P1.vcd");
    $dumpvars(0, Test_bench_P1);
end
endmodule

Prueba_P1.vcd
$date
	Mon Jul 26 15:20:39 2021
$end
$version
	Icarus Verilog
$end
$timescale
	1s
$end
$scope module Test_bench_P1 $end
$var wire 1 ! WS_OR3 $end
$var wire 1 " WS_OR2 $end
$var reg 1 # K $end
$var reg 1 $ M $end
$var reg 1 % X $end
$var reg 1 & Y $end
$var reg 1 ' Z $end
$var integer 32 ( i [31:0] $end
$scope module Indtance0 $end
$var wire 1 # K $end
$var wire 1 $ M $end
$var wire 1 ) S_1 $end
$var wire 1 * S_10 $end
$var wire 1 + S_11 $end
$var wire 1 , S_12 $end
$var wire 1 - S_13 $end
$var wire 1 . S_15 $end
$var wire 1 / S_17 $end
$var wire 1 0 S_19 $end
$var wire 1 1 S_2 $end
$var wire 1 2 S_3 $end
$var wire 1 3 S_4 $end
$var wire 1 4 S_5 $end
$var wire 1 5 S_6 $end
$var wire 1 6 S_7 $end
$var wire 1 7 S_8 $end
$var wire 1 8 S_9 $end
$var wire 1 " S_OR2 $end
$var wire 1 % X $end
$var wire 1 & Y $end
$var wire 1 ' Z $end
$var wire 1 9 noZ $end
$var wire 1 : noY $end
$var wire 1 ; noX $end
$var wire 1 < noM $end
$var wire 1 = noK $end
$upscope $end
$scope module Indtance1 $end
$var wire 1 # K $end
$var wire 1 $ M $end
$var wire 1 ! S_OR3 $end
$var wire 1 % X $end
$var wire 1 & Y $end
$var wire 1 ' Z $end
$var wire 1 > out_1 $end
$var wire 1 ? out_2 $end
$var wire 1 @ out_3 $end
$var wire 1 A out_4 $end
$var wire 1 B out_5 $end
$var wire 1 C out_6 $end
$var wire 1 D noZ $end
$var wire 1 E noY $end
$var wire 1 F noX $end
$var wire 1 G noM $end
$var wire 1 H noK $end
$upscope $end
$upscope $end
$enddefinitions $end
#0
$dumpvars
1H
1G
1F
1E
1D
1C
0B
0A
0@
0?
1>
1=
1<
1;
1:
19
08
07
06
05
04
03
02
01
00
0/
0.
1-
0,
0+
0*
0)
b0 (
0'
0&
0%
0$
0#
1"
1!
$end
#10
0!
0"
0-
0C
0>
0<
0G
1$
b1 (
#20
1"
1)
1!
1@
0-
1C
1>
0=
0H
1#
1<
1G
0$
b10 (
#30
11
0)
0C
0>
0<
0G
1$
b11 (
#40
12
0-
0@
01
0)
0C
1>
09
0D
1'
1=
1H
0#
1<
1G
0$
b100 (
#50
0"
0!
02
0>
0<
0G
1$
b101 (
#60
1"
1!
13
02
1>
0=
0H
1#
1<
1G
0$
b110 (
#70
0"
0!
03
0>
0<
0G
1$
b111 (
#80
1"
1.
0-
1!
1C
02
03
0>
0:
0E
1&
19
1D
0'
1=
1H
0#
1<
1G
0$
b1000 (
#90
0"
0!
0.
0C
0<
0G
1$
b1001 (
#100
1"
14
1!
0.
1C
0=
0H
1#
1<
1G
0$
b1010 (
#110
1!
15
04
1?
0C
0<
0G
1$
b1011 (
#120
0"
0!
0.
05
04
0?
0C
09
0D
1'
1=
1H
0#
1<
1G
0$
b1100 (
#130
0<
0G
1$
b1101 (
#140
0=
0H
1#
1<
1G
0$
b1110 (
#150
1"
1!
16
1?
0<
0G
1$
b1111 (
#160
0"
0!
0.
06
0?
0;
0F
1%
1:
1E
0&
19
1D
0'
1=
1H
0#
1<
1G
0$
b10000 (
#170
1"
1!
17
1A
1B
0<
0G
1$
b10001 (
#180
1!
18
1@
07
0A
0B
0=
0H
1#
1<
1G
0$
b10010 (
#190
1/
08
1A
1B
0<
0G
1$
b10011 (
#200
0!
0"
0@
0/
08
0A
0B
09
0D
1'
1=
1H
0#
1<
1G
0$
b10100 (
#210
1"
1!
1*
1A
0<
0G
1$
b10101 (
#220
0"
0!
0*
0A
0=
0H
1#
1<
1G
0$
b10110 (
#230
1!
1"
10
1A
0<
0G
1$
b10111 (
#240
0!
0"
00
0A
0:
0E
1&
19
1D
0'
1=
1H
0#
1<
1G
0$
b11000 (
#250
1"
1!
1+
1B
0<
0G
1$
b11001 (
#260
0"
0!
0+
0B
0=
0H
1#
1<
1G
0$
b11010 (
#270
1"
1!
1,
1B
0<
0G
1$
b11011 (
#280
0"
0!
0,
0B
09
0D
1'
1=
1H
0#
1<
1G
0$
b11100 (
#290
0<
0G
1$
b11101 (
#300
0=
0H
1#
1<
1G
0$
b11110 (
#310
0<
0G
1$
b11111 (
#320
b100000 (
