AND_inciso3.v

module AND_inciso3(
    output out_7,
    output out_8,
    output S_OR3,
   
    input X,
    input Y,
    input Z,
    input K,
    input M
    
);

assign noX = !X;
assign noY = !Y;
assign noZ = !Z;
assign noK = !K;
assign noM = !M;

assign out_9 = noX & noZ & noM;//implicante 1
assign out_1 = noX & noY & noM;//implicante 3
assign out_2 = noX & Y & K & M;//implicante 8
assign out_3=  noY & noZ & K;//implicante 4
//assign out_4 = noX & noZ & K;//implicante 2
assign out_5 = X & noY & M; //implicante 10
assign out_6 = X & noZ & M; //implicante 9
assign S_OR3 = (out_1)|(out_2)|(out_3)|(out_5)|(out_6)|(out_9);
assign out_7 = (~X & ~Y & ~M) | (~X & Y & K & M) | (~Y & ~Z & K) | (~X & ~Z & ~M) | (X & ~Y & M) | (X & ~Z & M);
//assign out_7 = (~X & ~Y & ~M) | (~X & Y & K & M) | (~Y & ~Z & K) | (~X & ~Z & K) | (X & ~Y & M) | (X & ~Z & M);
assign out_8 = (noX&noY&noM) | (noX&Y&K&M) | (noY&noZ&K) | (noX&noZ&noM) | (X&noY&M) | (X&noZ&M);
               
endmodule

AND_inciso2.v

module AND_inciso2(
    output S_OR2,
    output S_OR4,
    output S_OR5,
    input X,
    input Y,
    input Z,
    input K,
    input M   
);

assign noX = !X;
assign noY = !Y;
assign noZ = !Z;
assign noK = !K;
assign noM = !M;

assign S_1 = (noX)&(noY)&(noZ)&(K)&(noM);//m2
assign S_2 = (noX)&(noY)&(noZ)&(K)&(M);//m3
assign S_3 = (noX)&(noY)&(Z)&(noK)&(noM);//m4
assign S_4 = (noX)&(noY)&(Z)&(K)&(noM);//m6
assign S_5 = (noX)&(Y)&(noZ)&(K)&(noM);//m10
assign S_6=  (noX)&(Y)&(noZ)&(K)&(M);//m11
assign S_7 = (noX)&(Y)&(Z)&(K)&(M);//m15
assign S_8 = (X)&(noY)&(noZ)&(noK)&(M);//m17
assign S_9 = (X)&(noY)&(noZ)&(K)&(noM);//m18
assign S_10 = (X)&(noY)&(Z)&(noK)&(M);//m21
assign S_11 = (X)&(Y)&(noZ)&(noK)&(M);//m25
assign S_12 = (X)&(Y)&(noZ)&(K)&(M);//m27
/*
assign S_13 = (noX)&(noY)&(noZ)&(noK)&(noM);//x0
assign S_14 = (noX)&(noY)&(Z)&(noK)&(M);//x5
assign S_15 = (noX)&(Y)&(noZ)&(noK)&(noM);//x8
assign S_16 = (noX)&(Y)&(noZ)&(noK)&(M);//x9
assign S_17 = (X)&(noY)&(noZ)&(K)&(M);//x19
assign S_18 = (X)&(noY)&(Z)&(noK)&(noM);//x20
assign S_19 = (X)&(noY)&(Z)&(K)&(M);//x23
assign S_20 = (X)&(Y)&(noZ)&(noK)&(noM);//x24
*/
assign S_13 = (noX)&(noY)&(noZ)&(noK)&(noM);//x0
//assign S_14 = (noX)&(noY)&(Z)&(noK)&(M);//x5
assign S_15 = (noX)&(Y)&(noZ)&(noK)&(noM);//x8
//assign S_16 = (noX)&(Y)&(noZ)&(noK)&(M);//x9
assign S_17 = (X)&(noY)&(noZ)&(K)&(M);//x19
//assign S_18 = (X)&(noY)&(Z)&(noK)&(noM);//x20
assign S_19 = (X)&(noY)&(Z)&(K)&(M);//x23
//assign S_20 = (X)&(Y)&(noZ)&(noK)&(noM);//x24

//assign S_OR2 = (S_1)|(S_2)|(S_3)|(S_4)|(S_5)|(S_6)|(S_7)|(S_8)|(S_9)|(S_10)|(S_11)|(S_12);
//assign S_OR2 = (S_1)|(S_2)|(S_3)|(S_4)|(S_5)|(S_6)|(S_7)|(S_8)|(S_9)|(S_10)|(S_11)|(S_12)|(S_13)|(S_14)|(S_15)|(S_16)|(S_17)|(S_18)|(S_19)|(S_20);
assign S_OR2 = (S_1)|(S_2)|(S_3)|(S_4)|(S_5)|(S_6)|(S_7)|(S_8)|(S_9)|(S_10)|(S_11)|(S_12)|(S_13)|(S_15)|(S_17)|(S_19);
assign S_OR4 = (noX&noY&noZ&K&noM)| (noX&noY&noZ&K&M)| (noX&noY&Z&noK&noM)| (noX&noY&Z&K&noM)| (noX&Y&noZ&K&noM)| (noX&Y&noZ&K&M)| (noX&Y&Z&K&M)| (X&noY&noZ&noK&M)| (X&noY&noZ&K&noM)| (X&noY&Z&noK&M)| (X&Y&noZ&noK&M)| (X&Y&noZ&K&M);  
assign S_OR5 = (noX&noY&noZ&K&noM)| (noX&noY&noZ&K&M)| (noX&noY&Z&noK&noM)| (noX&noY&Z&K&noM)| (noX&Y&noZ&K&noM)| (noX&Y&noZ&K&M)| (noX&Y&Z&K&M)| (X&noY&noZ&noK&M)| (X&noY&noZ&K&noM)| (X&noY&Z&noK&M)| (X&Y&noZ&noK&M)| (X&Y&noZ&K&M)|(noX&noY&noZ&noK&noM)|(noX&Y&noZ&noK&noM)|(X&noY&noZ&K&M)|(X&noY&Z&K&M);  

endmodule

test_bench_P1.v
`include "AND_inciso3.v"
`include "AND_inciso2.v"


module Test_bench_P1;
    reg X, Y,Z ,K, M; // Entradas
    wire WS_OR2, WS_OR3,WS_OR4,WS_OR5, Wout_7,Wout_8;  // Salidas
    integer i;

    AND_inciso2 Indtance0 ( WS_OR2,WS_OR4,WS_OR5, X, Y, Z,K,M);
    AND_inciso3 Indtance1 (WS_OR3,Wout_7,Wout_8, X, Y, Z,K,M);
    
   
    
initial begin

    // Estímulo
    // Para iniciar en 00000
    X <= 0;Y <= 0;Z <= 0;K <= 0;M <= 0;

    for(i = 0; i < 32; i = i + 1) 
        begin
            {X,Y,Z,K,M} = i; 
            #10; 
        end   
end
   
initial begin
    $monitor("A continuacion la tabla de verdad usada:");
    $monitor("X=%0b Y=%0b Z=%0b K=%0b M=%0b ", X,Y,Z,K,M);
    // Crear archivo .vcd para gtkwave
    $dumpfile("Prueba_P1.vcd");
    $dumpvars(0, Test_bench_P1);
end
endmodule

Prueba_P1.vcd
$date
	Mon Jul 26 14:58:47 2021
$end
$version
	Icarus Verilog
$end
$timescale
	1s
$end
$scope module Test_bench_P1 $end
$var wire 1 ! Wout_8 $end
$var wire 1 " Wout_7 $end
$var wire 1 # WS_OR5 $end
$var wire 1 $ WS_OR4 $end
$var wire 1 % WS_OR3 $end
$var wire 1 & WS_OR2 $end
$var reg 1 ' K $end
$var reg 1 ( M $end
$var reg 1 ) X $end
$var reg 1 * Y $end
$var reg 1 + Z $end
$var integer 32 , i [31:0] $end
$scope module Indtance0 $end
$var wire 1 ' K $end
$var wire 1 ( M $end
$var wire 1 - S_1 $end
$var wire 1 . S_10 $end
$var wire 1 / S_11 $end
$var wire 1 0 S_12 $end
$var wire 1 1 S_13 $end
$var wire 1 2 S_15 $end
$var wire 1 3 S_17 $end
$var wire 1 4 S_19 $end
$var wire 1 5 S_2 $end
$var wire 1 6 S_3 $end
$var wire 1 7 S_4 $end
$var wire 1 8 S_5 $end
$var wire 1 9 S_6 $end
$var wire 1 : S_7 $end
$var wire 1 ; S_8 $end
$var wire 1 < S_9 $end
$var wire 1 & S_OR2 $end
$var wire 1 $ S_OR4 $end
$var wire 1 # S_OR5 $end
$var wire 1 ) X $end
$var wire 1 * Y $end
$var wire 1 + Z $end
$var wire 1 = noZ $end
$var wire 1 > noY $end
$var wire 1 ? noX $end
$var wire 1 @ noM $end
$var wire 1 A noK $end
$upscope $end
$scope module Indtance1 $end
$var wire 1 ' K $end
$var wire 1 ( M $end
$var wire 1 ! S_OR3 $end
$var wire 1 ) X $end
$var wire 1 * Y $end
$var wire 1 + Z $end
$var wire 1 B out_1 $end
$var wire 1 C out_2 $end
$var wire 1 D out_3 $end
$var wire 1 E out_5 $end
$var wire 1 F out_6 $end
$var wire 1 % out_7 $end
$var wire 1 " out_8 $end
$var wire 1 G out_9 $end
$var wire 1 H noZ $end
$var wire 1 I noY $end
$var wire 1 J noX $end
$var wire 1 K noM $end
$var wire 1 L noK $end
$upscope $end
$upscope $end
$enddefinitions $end
#0
$dumpvars
1L
1K
1J
1I
1H
1G
0F
0E
0D
0C
1B
1A
1@
1?
1>
1=
0<
0;
0:
09
08
07
06
05
04
03
02
11
00
0/
0.
0-
b0 ,
0+
0*
0)
0(
0'
1&
1%
0$
1#
1"
1!
$end
#10
0%
0"
0!
0#
0&
01
0B
0G
0@
0K
1(
b1 ,
#20
1$
1#
1&
1%
1"
1-
1!
1D
01
1B
1G
0A
0L
1'
1@
1K
0(
b10 ,
#30
15
0-
0B
0G
0@
0K
1(
b11 ,
#40
16
01
0D
05
0-
1B
0G
0=
0H
1+
1A
1L
0'
1@
1K
0(
b100 ,
#50
0#
0&
0$
0%
0"
0!
06
0B
0@
0K
1(
b101 ,
#60
1#
1&
1$
1%
1"
1!
17
06
1B
0A
0L
1'
1@
1K
0(
b110 ,
#70
0#
0&
0$
0%
0"
0!
07
0B
0@
0K
1(
b111 ,
#80
0$
1#
1&
1%
1"
12
01
1!
1G
06
07
0B
0>
0I
1*
1=
1H
0+
1A
1L
0'
1@
1K
0(
b1000 ,
#90
0%
0#
0&
0"
0!
02
0G
0@
0K
1(
b1001 ,
#100
1$
1%
1#
1&
1"
18
1!
02
1G
0A
0L
1'
1@
1K
0(
b1010 ,
#110
1%
1"
1!
19
08
1C
0G
0@
0K
1(
b1011 ,
#120
0&
0#
0$
0!
0%
0"
02
09
08
0C
0G
0=
0H
1+
1A
1L
0'
1@
1K
0(
b1100 ,
#130
0@
0K
1(
b1101 ,
#140
0A
0L
1'
1@
1K
0(
b1110 ,
#150
1&
1#
1$
1!
1%
1"
1:
1C
0@
0K
1(
b1111 ,
#160
0&
0#
0$
0!
0%
0"
02
0:
0C
0?
0J
1)
1>
1I
0*
1=
1H
0+
1A
1L
0'
1@
1K
0(
b10000 ,
#170
1&
1#
1$
1!
1%
1"
1;
1E
1F
0@
0K
1(
b10001 ,
#180
1!
1%
1"
1<
1D
0;
0E
0F
0A
0L
1'
1@
1K
0(
b10010 ,
#190
0$
13
0<
1E
1F
0@
0K
1(
b10011 ,
#200
0!
0%
0"
0$
0&
0#
0D
03
0<
0E
0F
0=
0H
1+
1A
1L
0'
1@
1K
0(
b10100 ,
#210
1&
1#
1$
1!
1%
1"
1.
1E
0@
0K
1(
b10101 ,
#220
0&
0#
0$
0!
0%
0"
0.
0E
0A
0L
1'
1@
1K
0(
b10110 ,
#230
1!
1%
1"
1&
1#
14
1E
0@
0K
1(
b10111 ,
#240
0!
0%
0"
0&
0#
04
0E
0>
0I
1*
1=
1H
0+
1A
1L
0'
1@
1K
0(
b11000 ,
#250
1&
1#
1$
1!
1%
1"
1/
1F
0@
0K
1(
b11001 ,
#260
0&
0#
0$
0!
0%
0"
0/
0F
0A
0L
1'
1@
1K
0(
b11010 ,
#270
1&
1#
1!
1$
1%
1"
10
1F
0@
0K
1(
b11011 ,
#280
0&
0#
0!
0$
0%
0"
00
0F
0=
0H
1+
1A
1L
0'
1@
1K
0(
b11100 ,
#290
0@
0K
1(
b11101 ,
#300
0A
0L
1'
1@
1K
0(
b11110 ,
#310
0@
0K
1(
b11111 ,
#320
b100000 ,
